{
  "slug": "pendulum_pin_radius_change",
  "originalNumber": "第5题",
  "skip": false,
  "model": "圆周运动半径突变模型",
  "id": "circular_motion_pendulum_pin_radius_change",
  "chapter": "圆周运动",
  "title": "Circular Motion - 悬线碰钉子时的圆周运动物理量变化",
  "question": "如图所示，长为\\(L\\)的悬线固定在\\(O\\)点，在\\(O\\)点正下方有一钉子\\(C\\)，\\(OC\\)距离为\\(\\frac{L}{2}\\)，把悬线另一端的小球\\(m\\)拉到跟悬点在同一水平面上无初速度释放，小球运动到悬点正下方时悬线碰到钉子，则小球的（ ）",
  "options": [
    "A. 线速度突然增大为原来的2倍",
    "B. 角速度突然增大为原来的2倍",
    "C. 向心加速度突然增大为原来的2倍",
    "D. 悬线拉力突然增大为原来的2倍"
  ],
  "answer": "【待校对】",
  "analysis": {
    "title": "悬线碰钉子的圆周运动分析",
    "content": "小球运动到悬点正下方时，悬线碰到钉子，转动半径变为原来的\\(\\frac{1}{2}\\)，瞬间线速度因无切向力保持不变，结合圆周运动的线速度、角速度、向心加速度和向心力公式分析各选项。【待校对】"
  },
  "animation": {
    "enabled": false,
    "level": "none",
    "type": "none",
    "playable": false,
    "interactive": false,
    "params": {},
    "timeline": {
      "duration": 0,
      "loop": false
    },
    "forces": []
  },
  "knowledge": [
    "圆周运动的线速度",
    "角速度与线速度的关系",
    "向心加速度",
    "向心力公式"
  ],
  "source": {
    "title": "圆周运动章节",
    "text": "第5题",
    "page": ""
  },
  "steps": [
    {
      "stepId": 1,
      "title": "分析碰钉子瞬间的线速度",
      "content": "小球从水平位置释放，只有重力做功，机械能守恒，到达最低点时悬线拉力为法向力，不改变线速度大小，故线速度瞬间不变。",
      "knowledge": [
        "机械能守恒",
        "圆周运动线速度"
      ],
      "commonMistakes": [
        "错误认为线速度会因半径突变而改变"
      ]
    },
    {
      "stepId": 2,
      "title": "分析角速度的变化",
      "content": "角速度公式为\\(\\omega = \\frac{v}{r}\\)，碰钉子后转动半径\\(r\\)变为\\(\\frac{L}{2}\\)，线速度\\(v\\)不变，因此角速度变为原来的2倍。",
      "knowledge": [
        "角速度与线速度的关系"
      ],
      "commonMistakes": [
        "忽略线速度不变的条件，直接认为角速度与半径成反比"
      ]
    },
    {
      "stepId": 3,
      "title": "分析向心加速度和拉力的变化",
      "content": "向心加速度\\(a = \\frac{v^2}{r}\\)，变为原来的2倍；悬线拉力\\(T = mg + \\frac{mv^2}{r}\\)，代入推导可知拉力并非原来的2倍。",
      "knowledge": [
        "向心加速度",
        "向心力公式"
      ],
      "commonMistakes": [
        "误将拉力变化等同于向心加速度变化，忽略重力的影响"
      ]
    }
  ],
  "summary": {
    "title": "悬线碰钉子的圆周运动物理量分析",
    "content": "本题考查圆周运动中半径突变时各物理量的变化规律，核心是线速度在瞬间保持不变，结合角速度、向心加速度和向心力公式推导各选项，需明确各物理量的决定因素。"
  }
}
