{
  "slug": "example6",
  "originalNumber": "例6",
  "skip": false,
  "skipReason": "",
  "model": "皮带传动向心加速度",
  "id": "circular_motion_example6",
  "chapter": "圆周运动",
  "title": "例6：皮带传动向心加速度",
  "question": "大轮通过皮带带动小轮转动，皮带与两轮无滑动。大轮半径是小轮半径的 \\(2\\) 倍，大轮上 \\(S\\) 点到转轴的距离是大轮半径的一半。已知大轮边缘 \\(P\\) 点的向心加速度为 \\(10\\,\\mathrm{m/s^2}\\)，求 \\(S\\) 点和小轮边缘 \\(Q\\) 点的向心加速度。",
  "options": [],
  "answer": "\\(a_S=5\\,\\mathrm{m/s^2}\\)，\\(a_Q=20\\,\\mathrm{m/s^2}\\)",
  "analysis": {
    "title": "解析",
    "content": "同一大轮上角速度相等，\\(a=\\omega^2r\\)，所以 \\(S\\) 点半径为 \\(P\\) 点一半，\\(a_S=5\\,\\mathrm{m/s^2}\\)。皮带无滑动，两轮边缘线速度相等，\\(a=\\frac{v^2}{r}\\)，小轮半径是大轮一半，所以 \\(a_Q=20\\,\\mathrm{m/s^2}\\)。"
  },
  "animation": {
    "enabled": false,
    "level": "none",
    "type": "none",
    "playable": false,
    "interactive": false,
    "params": {}
  },
  "knowledge": [
    "向心加速度",
    "同轴转动角速度相同",
    "皮带传动线速度相同"
  ],
  "source": {
    "title": "圆周运动",
    "text": "例6",
    "page": "",
    "hidden": true
  },
  "steps": [
    {
      "stepId": 1,
      "title": "同一大轮比较",
      "content": "同一刚体上角速度相等，\\(a=\\omega^2r\\)。\\(S\\) 点半径是 \\(P\\) 点一半，所以 \\(a_S=5\\,\\mathrm{m/s^2}\\)。",
      "knowledge": [
        "向心加速度",
        "同轴转动角速度相同",
        "皮带传动线速度相同"
      ],
      "commonMistakes": []
    },
    {
      "stepId": 2,
      "title": "皮带边缘比较",
      "content": "皮带无滑动时两轮边缘线速度相等，\\(a=\\frac{v^2}{r}\\)。小轮半径是大轮一半，所以边缘向心加速度变为 \\(2\\) 倍。",
      "knowledge": [
        "向心加速度",
        "同轴转动角速度相同",
        "皮带传动线速度相同"
      ],
      "commonMistakes": []
    },
    {
      "stepId": 3,
      "title": "得到结果",
      "content": "由 \\(a_P=10\\,\\mathrm{m/s^2}\\)，得 \\(a_S=5\\,\\mathrm{m/s^2}\\)，\\(a_Q=20\\,\\mathrm{m/s^2}\\)。",
      "knowledge": [
        "向心加速度",
        "同轴转动角速度相同",
        "皮带传动线速度相同"
      ],
      "commonMistakes": []
    }
  ],
  "summary": {
    "title": "总结",
    "content": "本题考查了同轴转动和皮带传动中向心加速度的计算，需区分角速度相同和线速度相同两种情形。"
  },
  "images": [],
  "practice": {
    "title": "近似题：皮带传动向心加速度",
    "question": "大轮半径是小轮半径的 \\(3\\) 倍，皮带不打滑。大轮边缘点 \\(P\\) 的向心加速度为 \\(12\\,\\mathrm{m/s^2}\\)，大轮半径一半处点 \\(S\\) 与小轮边缘点 \\(Q\\) 的向心加速度分别是多少？",
    "answer": "同轴点 \\(a=\\omega^2r\\)，所以 \\(a_S=\\frac{1}{2}a_P=6\\,\\mathrm{m/s^2}\\)。皮带传动边缘线速度相等，\\(a=\\frac{v^2}{r}\\)，小轮半径为大轮 \\(\\frac{1}{3}\\)，所以 \\(a_Q=3a_P=36\\,\\mathrm{m/s^2}\\)。",
    "thinking": "同一个轮用角速度相等，两个轮边缘用线速度相等。"
  },
  "analysisText": "同一大轮上角速度相等，\\(a=\\omega^2r\\)，所以 \\(S\\) 点半径为 \\(P\\) 点一半，\\(a_S=5\\,\\mathrm{m/s^2}\\)。皮带无滑动，两轮边缘线速度相等，\\(a=\\frac{v^2}{r}\\)，小轮半径是大轮一半，所以 \\(a_Q=20\\,\\mathrm{m/s^2}\\)。"
}
